obsidianrag/__init__.py
obsidianrag/__main__.py
obsidianrag/config.py
obsidianrag/api/__init__.py
obsidianrag/api/server.py
obsidianrag/cli/__init__.py
obsidianrag/cli/main.py
obsidianrag/core/__init__.py
obsidianrag/core/db_service.py
obsidianrag/core/metadata_tracker.py
obsidianrag/core/qa_agent.py
obsidianrag/core/qa_service.py
obsidianrag/core/rag.py
obsidianrag/utils/__init__.py
obsidianrag/utils/logger.py
obsidianrag/utils/ollama.py
obsidianrag-3.0.2.dist-info/METADATA
obsidianrag-3.0.2.dist-info/WHEEL
obsidianrag-3.0.2.dist-info/entry_points.txt
obsidianrag-3.0.2.dist-info/RECORD
