Metadata-Version: 2.4
Name: obsidianrag
Version: 3.0.2
Summary: RAG system for querying Obsidian notes using LangGraph and local LLMs
Project-URL: Homepage, https://github.com/Vasallo94/ObsidianRAG
Project-URL: Repository, https://github.com/Vasallo94/ObsidianRAG
Project-URL: Documentation, https://github.com/Vasallo94/ObsidianRAG#readme
Project-URL: Issues, https://github.com/Vasallo94/ObsidianRAG/issues
Author: Enrique Vasallo
License: MIT
Keywords: chromadb,langchain,langgraph,obsidian,ollama,plugin,rag
Classifier: Development Status :: 4 - Beta
Classifier: Intended Audience :: Developers
Classifier: Intended Audience :: End Users/Desktop
Classifier: License :: OSI Approved :: MIT License
Classifier: Operating System :: OS Independent
Classifier: Programming Language :: Python :: 3
Classifier: Programming Language :: Python :: 3.11
Classifier: Programming Language :: Python :: 3.12
Classifier: Topic :: Scientific/Engineering :: Artificial Intelligence
Classifier: Topic :: Text Processing :: Indexing
Requires-Python: >=3.11
Requires-Dist: chromadb>=0.5.0
Requires-Dist: fastapi>=0.112.0
Requires-Dist: httpx>=0.27.0
Requires-Dist: langchain-chroma>=0.2.0
Requires-Dist: langchain-community>=0.3.0
Requires-Dist: langchain-core>=0.3.0
Requires-Dist: langchain-huggingface>=0.1.0
Requires-Dist: langchain-ollama>=0.2.0
Requires-Dist: langchain-text-splitters>=0.3.0
Requires-Dist: langchain>=0.3.0
Requires-Dist: langgraph>=0.2.0
Requires-Dist: pydantic-settings>=2.0.0
Requires-Dist: pydantic>=2.0.0
Requires-Dist: python-dotenv>=1.0.0
Requires-Dist: rank-bm25>=0.2.2
Requires-Dist: requests>=2.32.0
Requires-Dist: rich>=13.0.0
Requires-Dist: sentence-transformers>=3.0.0
Requires-Dist: torch>=2.0.0
Requires-Dist: transformers>=4.40.0
Requires-Dist: typer>=0.12.0
Requires-Dist: uvicorn>=0.30.0
Provides-Extra: dev
Requires-Dist: black>=24.0.0; extra == 'dev'
Requires-Dist: mypy>=1.8.0; extra == 'dev'
Requires-Dist: pytest-asyncio>=0.23.0; extra == 'dev'
Requires-Dist: pytest-cov>=4.0.0; extra == 'dev'
Requires-Dist: pytest>=8.0.0; extra == 'dev'
Requires-Dist: ruff>=0.3.0; extra == 'dev'
